odoo10_addon_analytic_operating_unit-10.0.1.0.0-py2.7-nspkg.pth
odoo10_addon_analytic_operating_unit-10.0.1.0.0.dist-info/top_level.txt
odoo10_addon_analytic_operating_unit-10.0.1.0.0.dist-info/WHEEL
odoo10_addon_analytic_operating_unit-10.0.1.0.0.dist-info/RECORD
odoo10_addon_analytic_operating_unit-10.0.1.0.0.dist-info/metadata.json
odoo10_addon_analytic_operating_unit-10.0.1.0.0.dist-info/DESCRIPTION.rst
odoo10_addon_analytic_operating_unit-10.0.1.0.0.dist-info/METADATA
odoo10_addon_analytic_operating_unit-10.0.1.0.0.dist-info/namespace_packages.txt
odoo/addons/analytic_operating_unit/__manifest__.py
odoo/addons/analytic_operating_unit/__init__.py
odoo/addons/analytic_operating_unit/README.rst
odoo/addons/analytic_operating_unit/security/analytic_account_security.xml
odoo/addons/analytic_operating_unit/models/__init__.py
odoo/addons/analytic_operating_unit/models/account_analytic_account.py
odoo/addons/analytic_operating_unit/views/analytic_account_view.xml
odoo/addons/analytic_operating_unit/static/description/icon.png
